<?xml version="1.0" encoding="UTF-8" standalone="yes"?>
<map>
  (<!-- 17x11 Tiles -->)
  <tiles>
    00000000000000000
    00000000000000000
    00000000000000000
    00000000000000000
    00000000000000000
    00000000000000000
    00000000000000000
    00000000000000000
    00000000000000000
    00000000000000000
    00000000000000000
  </tiles>
  <blocks>
    <row_2>01010101010101010</row_2>
    <row_4>01010101010101010</row_4>
    <row_6>01010101010101010</row_6>
    <row_8>01010101010101010</row_8>
    <row_10>01010101010101010</row_10>
  </blocks>
  <rocks>
    <probability>60%</probability>
    <clean>
      <row_1>11000000000000011</row_1>
      <row_2>10000000000000001</row_2>
      <row_10>10000000000000001</row_10>
      <row_11>11000000000000011</row_11>
    </clean>
  </rocks>
  <powerups>
    <droprate>30%</droprate>
  </powerups>
</map>
